pyroots/__init__.py
pyroots/base.py
pyroots/bisect.py
pyroots/brent.py
pyroots/ridder.py
pyroots/utils.py
pyroots-0.5.0.dist-info/WHEEL
pyroots-0.5.0.dist-info/METADATA
pyroots-0.5.0.dist-info/RECORD
